aws_authenticate_inline/__init__.py
aws_authenticate_inline-1.0.0.dist-info/LICENSE
aws_authenticate_inline-1.0.0.dist-info/METADATA
aws_authenticate_inline-1.0.0.dist-info/WHEEL
aws_authenticate_inline-1.0.0.dist-info/top_level.txt
aws_authenticate_inline-1.0.0.dist-info/RECORD
