Metadata-Version: 2.1
Name: aws-authenticate-inline
Version: 1.0.0
Summary: Authenticate to AWS inline
Home-page: https://github.com/nuchi/aws-authenticate-inline
Author: Haggai Nuchi
Author-email: haggai@haggainuchi.com
License: MIT
Keywords: aws,botocore,boto3,authenticate,jupyter,colab
Platform: any
License-File: LICENSE
Requires-Dist: botocore (>=1.0)
